odoo/addons/shopinvader_schema_sale/README.rst
odoo/addons/shopinvader_schema_sale/__init__.py
odoo/addons/shopinvader_schema_sale/__manifest__.py
odoo/addons/shopinvader_schema_sale/i18n/shopinvader_schema_sale.pot
odoo/addons/shopinvader_schema_sale/readme/CONTRIBUTORS.rst
odoo/addons/shopinvader_schema_sale/readme/DESCRIPTION.rst
odoo/addons/shopinvader_schema_sale/schemas/__init__.py
odoo/addons/shopinvader_schema_sale/schemas/amount.py
odoo/addons/shopinvader_schema_sale/schemas/delivery.py
odoo/addons/shopinvader_schema_sale/schemas/invoicing.py
odoo/addons/shopinvader_schema_sale/schemas/sale.py
odoo/addons/shopinvader_schema_sale/schemas/sale_line.py
odoo/addons/shopinvader_schema_sale/static/description/index.html
odoo/addons/shopinvader_schema_sale/tests/__init__.py
odoo/addons/shopinvader_schema_sale/tests/common.py
odoo/addons/shopinvader_schema_sale/tests/test_sale_schema.py
odoo_addon_shopinvader_schema_sale-16.0.1.2.0.dist-info/METADATA
odoo_addon_shopinvader_schema_sale-16.0.1.2.0.dist-info/WHEEL
odoo_addon_shopinvader_schema_sale-16.0.1.2.0.dist-info/top_level.txt
odoo_addon_shopinvader_schema_sale-16.0.1.2.0.dist-info/RECORD
